GeneticFeatureSelection/__init__.py
GeneticFeatureSelection-1.0.6.dist-info/LICENSE.txt
GeneticFeatureSelection-1.0.6.dist-info/METADATA
GeneticFeatureSelection-1.0.6.dist-info/WHEEL
GeneticFeatureSelection-1.0.6.dist-info/top_level.txt
GeneticFeatureSelection-1.0.6.dist-info/RECORD
