Metadata-Version: 2.1
Name: GeneticFeatureSelection
Version: 1.0.6
Summary: GeneticFeatureSelection
Home-page: https://github.com/HindyDS/GeneticFeatureSelection
Author: Hindy Yuen
Author-email: hindy888@hotmail.com
License: MIT
Keywords: Genetic Feature Selection
Platform: UNKNOWN
Classifier: Development Status :: 3 - Alpha
Classifier: Intended Audience :: Developers
Classifier: Topic :: Software Development :: Build Tools
Classifier: License :: OSI Approved :: MIT License
Classifier: Programming Language :: Python :: 3.7
Classifier: Programming Language :: Python :: 3.8
Classifier: Programming Language :: Python :: 3.9
Requires-Python: >=3.6
